sdjson/__init__.py
sdjson/__init__.pyi
sdjson/py.typed
sdjson-0.5.0.dist-info/LICENSE
sdjson-0.5.0.dist-info/METADATA
sdjson-0.5.0.dist-info/WHEEL
sdjson-0.5.0.dist-info/entry_points.txt
sdjson-0.5.0.dist-info/RECORD
