Metadata-Version: 2.2
Name: sdjson
Version: 0.5.0
Summary: Custom JSON Encoder for Python utilising functools.singledispatch to support custom encoders for both Python's built-in classes and user-created classes, without as much legwork.
Author-email: Dominic Davis-Foster <dominic@davis-foster.co.uk>
License: MIT
Keywords: json,serialize,singledispatch
Home-page: https://github.com/domdfcoding/singledispatch-json
Project-URL: Issue Tracker, https://github.com/domdfcoding/singledispatch-json/issues
Project-URL: Source Code, https://github.com/domdfcoding/singledispatch-json
Project-URL: Documentation, https://singledispatch-json.readthedocs.io/en/latest
Platform: Windows
Platform: macOS
Platform: Linux
Classifier: Development Status :: 4 - Beta
Classifier: Intended Audience :: Developers
Classifier: License :: OSI Approved :: MIT License
Classifier: Operating System :: OS Independent
Classifier: Programming Language :: Python
Classifier: Programming Language :: Python :: 3 :: Only
Classifier: Programming Language :: Python :: 3.6
Classifier: Programming Language :: Python :: 3.7
Classifier: Programming Language :: Python :: 3.8
Classifier: Programming Language :: Python :: 3.9
Classifier: Programming Language :: Python :: 3.10
Classifier: Programming Language :: Python :: 3.11
Classifier: Programming Language :: Python :: 3.12
Classifier: Programming Language :: Python :: Implementation :: CPython
Classifier: Programming Language :: Python :: Implementation :: PyPy
Classifier: Topic :: Software Development :: Libraries :: Python Modules
Classifier: Topic :: Utilities
Classifier: Typing :: Typed
Requires-Python: >=3.6
Requires-Dist: domdf-python-tools>=2.5.2
Requires-Dist: typing-extensions>=3.7.4.3
